setup.py
scrapy_redis_cluster/__init__.py
scrapy_redis_cluster/bloomfilter.py
scrapy_redis_cluster/connection.py
scrapy_redis_cluster/defaults.py
scrapy_redis_cluster/dupefilter.py
scrapy_redis_cluster/picklecompat.py
scrapy_redis_cluster/pipelines.py
scrapy_redis_cluster/queue.py
scrapy_redis_cluster/scheduler.py
scrapy_redis_cluster/spiders.py
scrapy_redis_cluster/utils.py
scrapy_redis_cluster.egg-info/PKG-INFO
scrapy_redis_cluster.egg-info/SOURCES.txt
scrapy_redis_cluster.egg-info/dependency_links.txt
scrapy_redis_cluster.egg-info/requires.txt
scrapy_redis_cluster.egg-info/top_level.txt