Metadata-Version: 1.1
Name: scrapy-redis-cluster
Version: 0.4
Summary: scrapyd-redis的集群版
Home-page: https://github.com/thsheep/scrapy_redis_cluster
Author: thsheep
Author-email: thsheep@thsheep.com
License: MIT
Keywords: scrapy_redis_cluster
Platform: UNKNOWN
Classifier: License :: OSI Approved :: MIT License
Classifier: Programming Language :: Python :: 3.6
